pnadc/__init__.py
pnadc/__main__.py
pnadc/cli.py
pnadc/pnadc.py
pnadc/pypnad.py
pnadc/tools.py
pnadc-0.0.7.dist-info/AUTHORS.rst
pnadc-0.0.7.dist-info/LICENSE
pnadc-0.0.7.dist-info/METADATA
pnadc-0.0.7.dist-info/WHEEL
pnadc-0.0.7.dist-info/entry_points.txt
pnadc-0.0.7.dist-info/top_level.txt
pnadc-0.0.7.dist-info/RECORD
