Metadata-Version: 2.1
Name: pnadc
Version: 0.0.7
Summary: A python package to deal with IBGE-PNADc database.
Home-page: https://github.com/ppnasser/pnadc
Author: Patrick Parente Nasser
Author-email: patricknasser@gmail.com
License: LGPL-3.0-or-later
Project-URL: Documentation, https://pnadc.readthedocs.io/
Project-URL: Changelog, https://pnadc.readthedocs.io/en/latest/changelog.html
Project-URL: Issue Tracker, https://github.com/ppnasser/pnadc/issues
Platform: UNKNOWN
Classifier: Development Status :: 4 - Beta
Classifier: License :: OSI Approved :: GNU Lesser General Public License v3 or later (LGPLv3+)
Classifier: Programming Language :: Python :: 3.6
Classifier: Programming Language :: Python :: 3.7
Classifier: Programming Language :: Python :: 3.8
Classifier: Topic :: Utilities
Requires-Python: >=3.6.1
Requires-Dist: pandas (>=1.0)
Requires-Dist: xlrd (>=1.2)
Requires-Dist: tqdm (>=4.50.2)
